rs_mailer/__init__.py
rs_mailer-0.11.dist-info/LICENSE
rs_mailer-0.11.dist-info/METADATA
rs_mailer-0.11.dist-info/WHEEL
rs_mailer-0.11.dist-info/top_level.txt
rs_mailer-0.11.dist-info/RECORD
