Metadata-Version: 2.1
Name: rs-mailer
Version: 0.11
Summary: A really simple Python package for sending emails through SMTP servers.
Home-page: https://github.com/ronaldseoh/rs_mailer
Author: Ronald Seoh
Author-email: ronaldseoh@icloud.com
License: BSD-3
Platform: UNKNOWN
